odoo/addons/helpdesk_hide_email_send_parent/CHANGELOG.md
odoo/addons/helpdesk_hide_email_send_parent/README.rst
odoo/addons/helpdesk_hide_email_send_parent/__init__.py
odoo/addons/helpdesk_hide_email_send_parent/__manifest__.py
odoo/addons/helpdesk_hide_email_send_parent/i18n/ca_ES.po
odoo/addons/helpdesk_hide_email_send_parent/i18n/es.po
odoo/addons/helpdesk_hide_email_send_parent/models/__init__.py
odoo/addons/helpdesk_hide_email_send_parent/models/mail_message.py
odoo/addons/helpdesk_hide_email_send_parent/static/description/icon.png
odoo/addons/helpdesk_hide_email_send_parent/tests/__init__.py
odoo/addons/helpdesk_hide_email_send_parent/views/helpdesk_ticket_view.xml
odoo12_addon_helpdesk_hide_email_send_parent-12.0.1.0.0.dist-info/METADATA
odoo12_addon_helpdesk_hide_email_send_parent-12.0.1.0.0.dist-info/WHEEL
odoo12_addon_helpdesk_hide_email_send_parent-12.0.1.0.0.dist-info/top_level.txt
odoo12_addon_helpdesk_hide_email_send_parent-12.0.1.0.0.dist-info/RECORD
